migrant/__init__.py
migrant/backend.py
migrant/cli.py
migrant/engine.py
migrant/exceptions.py
migrant/py.typed
migrant/repository.py
migrant/tests/__init__.py
migrant/tests/conftest.py
migrant/tests/test_cli.py
migrant/tests/test_engine.py
migrant/tests/test_repo.py
migrant/tests/scripts/aaaa_first.py
migrant/tests/scripts/bbbb_second.py
migrant/tests/scripts/cccc_third.py
migrant-1.6.1.dist-info/LICENSE
migrant-1.6.1.dist-info/METADATA
migrant-1.6.1.dist-info/WHEEL
migrant-1.6.1.dist-info/entry_points.txt
migrant-1.6.1.dist-info/top_level.txt
migrant-1.6.1.dist-info/RECORD
