Metadata-Version: 2.2
Name: migrant
Version: 1.6.1
Summary: Database Migration Engine
Author-email: "Shoobx, Inc." <dev@shoobx.com>
License: MIT
Project-URL: Homepage, https://github.com/Shoobx/migrant/
Keywords: migration,version,database
Classifier: Development Status :: 2 - Pre-Alpha
Classifier: Intended Audience :: Developers
Classifier: Programming Language :: Python
Classifier: Programming Language :: Python :: 3
Classifier: Programming Language :: Python :: 3.7
Classifier: Programming Language :: Python :: 3.8
Classifier: Programming Language :: Python :: 3.9
Classifier: Programming Language :: Python :: 3.10
Classifier: Programming Language :: Python :: 3.11
Classifier: Programming Language :: Python :: Implementation :: CPython
Classifier: Natural Language :: English
Classifier: Operating System :: OS Independent
License-File: LICENSE
Requires-Dist: setuptools
Provides-Extra: test
Requires-Dist: coverage; extra == "test"
Requires-Dist: mock; extra == "test"
